screenagent/__init__.py
screenagent/config.ini
screenagent/screenagent.py
soundagent/__init__.py
soundagent/config.ini
soundagent/soundagent.py
vdr/__init__.py
vdr/config.ini
vdr/sentences.py
vdr/tools.py
vdr/vdr.py
vdr-2.0.4.dist-info/METADATA
vdr-2.0.4.dist-info/WHEEL
vdr-2.0.4.dist-info/top_level.txt
vdr-2.0.4.dist-info/RECORD
