Metadata-Version: 2.1
Name: vdr
Version: 2.0.4
Summary: A simple library to simulate a VDR.
Home-page: https://github.com/MaxouPicsou/VDR
Author: Maxence Lannuzel
Author-email: maxence.lannuzel@ecole-navale.fr
License: MIT
Keywords: vdr
Platform: UNKNOWN
Classifier: Development Status :: 4 - Beta
Classifier: Intended Audience :: Developers
Classifier: License :: OSI Approved :: MIT License
Classifier: Natural Language :: French
Classifier: Operating System :: POSIX :: Linux
Classifier: Programming Language :: Python :: 3.8
Classifier: Topic :: Software Development
Requires-Dist: pyautogui
Requires-Dist: configparser
